perprof_web/__init__.py
perprof_web/plotting.py
perprof_web/views.py
perprof_web-0.0.2.dist-info/LICENSE.md
perprof_web-0.0.2.dist-info/METADATA
perprof_web-0.0.2.dist-info/WHEEL
perprof_web-0.0.2.dist-info/top_level.txt
perprof_web-0.0.2.dist-info/RECORD
