Metadata-Version: 2.1
Name: perprof-web
Version: 0.0.2
Summary: Web interface for perprof-py
Author-email: Abel Soares Siqueira <abel.s.siqueira@gmail.com>
Project-URL: repository, https://github.com/abelsiqueira/perprof-web
Project-URL: documentation, https://abelsiqueira.com/perprof-web/
Keywords: benchmark,comparison,performance profile,flask
Classifier: Programming Language :: Python
Requires-Python: >=3.7
License-File: LICENSE.md
Requires-Dist: flask (<3,>=2)
Requires-Dist: perprof-py (<2,>=1.1.4)
Requires-Dist: matplotlib (<4,>=3)
Provides-Extra: dev
Requires-Dist: black ; extra == 'dev'
Requires-Dist: pre-commit ; extra == 'dev'
Requires-Dist: ruff ; extra == 'dev'
Requires-Dist: pylint ; extra == 'dev'
Requires-Dist: pytest ; extra == 'dev'
Requires-Dist: pytest-cov ; extra == 'dev'
Provides-Extra: docs
Requires-Dist: mkdocs ; extra == 'docs'
Requires-Dist: mkdocstrings[python] ; extra == 'docs'
Requires-Dist: mkdocs-material ; extra == 'docs'
Requires-Dist: mike ; extra == 'docs'
Provides-Extra: publishing
Requires-Dist: twine ; extra == 'publishing'
